discern/__init__.py
discern/discern_base.py
discern/discern_tabular.py
discern/fa_base.py
discern/fa_intg.py
discern/fa_lime.py
discern/fa_shap.py
discern/util.py
discern_xai-0.0.27.dist-info/LICENCE
discern_xai-0.0.27.dist-info/METADATA
discern_xai-0.0.27.dist-info/WHEEL
discern_xai-0.0.27.dist-info/top_level.txt
discern_xai-0.0.27.dist-info/RECORD
