Metadata-Version: 2.1
Name: discern-xai
Version: 0.0.27
Summary: DisCERN: Discovering Counterfactual Explanations using Relevance Features from Neighbourhoods
Home-page: https://github.com/RGU-Computing/discern-xai
Author: Anjana Wijekoon
Author-email: a.wijekoon1@rgu.ac.uk
Keywords: machine-learning explanation interpretability counterfactual
Classifier: Programming Language :: Python :: 3
Classifier: License :: OSI Approved :: MIT License
License-File: LICENCE
